mlflow_med_cli/__init__.py
mlflow_med_cli/main.py
mlflow_med_cli-0.1.0.dist-info/entry_points.txt
mlflow_med_cli-0.1.0.dist-info/WHEEL
mlflow_med_cli-0.1.0.dist-info/METADATA
mlflow_med_cli-0.1.0.dist-info/RECORD
