Metadata-Version: 2.1
Name: mlflow-med-cli
Version: 0.1.0
Summary: 
Author: hossay
Author-email: youhs4554@gmail.com
Requires-Python: >=3.8,<4.0
Classifier: Programming Language :: Python :: 3
Classifier: Programming Language :: Python :: 3.8
Classifier: Programming Language :: Python :: 3.9
Classifier: Programming Language :: Python :: 3.10
Classifier: Programming Language :: Python :: 3.11
Requires-Dist: typer (>=0.6.1,<0.7.0)
